odoo10_addon_l10n_fi_banks-10.0.1.0.0.99.dev3-py2.7-nspkg.pth
odoo/addons/l10n_fi_banks/README.rst
odoo/addons/l10n_fi_banks/__init__.py
odoo/addons/l10n_fi_banks/__manifest__.py
odoo/addons/l10n_fi_banks/data/res_bank.xml
odoo/addons/l10n_fi_banks/i18n/fi.po
odoo/addons/l10n_fi_banks/i18n/l10n_fi_banks.pot
odoo/addons/l10n_fi_banks/static/description/icon.png
odoo10_addon_l10n_fi_banks-10.0.1.0.0.99.dev3.dist-info/METADATA
odoo10_addon_l10n_fi_banks-10.0.1.0.0.99.dev3.dist-info/RECORD
odoo10_addon_l10n_fi_banks-10.0.1.0.0.99.dev3.dist-info/WHEEL
odoo10_addon_l10n_fi_banks-10.0.1.0.0.99.dev3.dist-info/namespace_packages.txt
odoo10_addon_l10n_fi_banks-10.0.1.0.0.99.dev3.dist-info/top_level.txt
